cumm_cu120-0.6.3.dist-info/RECORD
cumm_cu120-0.6.3.dist-info/METADATA
cumm_cu120-0.6.3.dist-info/WHEEL
cumm_cu120-0.6.3.dist-info/top_level.txt
cumm_cu120-0.6.3.dist-info/LICENSE
cumm_cu120.libs/libnvrtc-d7c32a86.so.12.0.140
cumm_cu120.libs/libnvrtc-builtins-8cb4db2d.so.12.0.140
cumm_cu120.libs/libcudart-5a077122.so.12.0.107
cumm/tensorview_bind_anno.pyi
cumm/bindings.py
cumm/inliner.py
cumm/__init__.py
cumm/tensorview_bind.py
cumm/common.py
cumm/__version__.py
cumm/constants.py
cumm/dtypes.py
cumm/perftools.py
cumm/core_cc.cpython-38-x86_64-linux-gnu.so
cumm/nvrtc/__init__.py
cumm/nvrtc/dev.py
cumm/services/__init__.py
cumm/services/nvrtc.py
cumm/inliner/prompt.py
cumm/inliner/__init__.py
cumm/inliner/cuda/__main__.py
cumm/inliner/cuda/__init__.py
cumm/inliner/cpu/__main__.py
cumm/inliner/cpu/__init__.py
cumm/conv/sparse_iters.py
cumm/conv/input_iters.py
cumm/conv/__init__.py
cumm/conv/main_real.py
cumm/conv/main.py
cumm/conv/main_real_spconv.py
cumm/conv/algo.py
cumm/conv/nvrtc_code.py
cumm/conv/params.py
cumm/conv/bases.py
cumm/conv/kernel.py
cumm/conv/algospec/__init__.py
cumm/conv/algospec/all.py
cumm/conv/algospec/core.py
cumm/conv/algospec/simt.py
cumm/conv/algospec/volta.py
cumm/conv/algospec/turing.py
cumm/lib/libcudadevrt.a
cumm/core_cc/__init__.pyi
cumm/core_cc/tensorview_bind.pyi
cumm/core_cc/csrc/__init__.pyi
cumm/core_cc/csrc/arrayref.pyi
cumm/cmds/__init__.py
cumm/cmds/include_path/__main__.py
cumm/cmds/include_path/__init__.py
cumm/tensorview/gemm.py
cumm/tensorview/__init__.py
cumm/tensorview/tvio.py
cumm/tensorview/utils.py
cumm/tensorview/creator.py
cumm/devapps/__init__.py
cumm/devapps/template.py
cumm/csrc/arrayref.py
cumm/csrc/__init__.py
cumm/develop/mathgen.py
cumm/develop/__init__.py
cumm/develop/eigendev.py
cumm/include/tensorview/cc17.h
cumm/include/tensorview/cuda_utils.h
cumm/include/tensorview/pybind.h
cumm/include/tensorview/kernel_utils.h
cumm/include/tensorview/pybind_utils.h
cumm/include/tensorview/simple_ops.h
cumm/include/tensorview/mp_helper.h
cumm/include/tensorview/prettyprint.h
cumm/include/tensorview/tensor.h
